spec_test/__init__.py
spec_test/cli.py
spec_test/collector.py
spec_test/contracts.py
spec_test/decorators.py
spec_test/prover.py
spec_test/pytest_plugin.py
spec_test/reporter.py
spec_test/runner.py
spec_test/types.py
spec_test/verifier.py
spec_test/skills/README.md
spec_test/skills/spec-feature/SKILL.md
spec_test/skills/spec-implement/SKILL.md
spec_test/skills/spec-issue/SKILL.md
spec_test/skills/spec-review/SKILL.md
spec_test/skills/spec-verify/SKILL.md
spec_test/skills/spec-workflow/SKILL.md
spec_test-0.3.4.dist-info/METADATA
spec_test-0.3.4.dist-info/WHEEL
spec_test-0.3.4.dist-info/entry_points.txt
spec_test-0.3.4.dist-info/RECORD
