Metadata-Version: 2.4
Name: spec-test
Version: 0.3.4
Summary: Make AI-generated code trustworthy through mathematical verification
Author: Pulse Team
License: MIT
Requires-Python: >=3.11
Requires-Dist: pydantic>=2.0.0
Requires-Dist: pytest-cov>=4.0.0
Requires-Dist: pytest>=8.0.0
Requires-Dist: rich>=13.0.0
Requires-Dist: typer>=0.9.0
Provides-Extra: all
Requires-Dist: z3-solver>=4.12.0; extra == 'all'
Provides-Extra: dev
Requires-Dist: mypy>=1.0.0; extra == 'dev'
Requires-Dist: pytest-cov>=4.0.0; extra == 'dev'
Requires-Dist: ruff>=0.1.0; extra == 'dev'
Provides-Extra: z3
Requires-Dist: z3-solver>=4.12.0; extra == 'z3'
